notimportchecker.py
NotImportChecker-0.0.1b1.dist-info/METADATA
NotImportChecker-0.0.1b1.dist-info/RECORD
NotImportChecker-0.0.1b1.dist-info/WHEEL
NotImportChecker-0.0.1b1.dist-info/top_level.txt
