Metadata-Version: 2.1
Name: NotImportChecker
Version: 0.0.1b1
Summary: A module to know if there are some modules imported that does not  exist
Home-page: https://github.com/pypa/sampleproject
Author: eamanu <Emmanuel Arias>
Author-email: eamanu@eamanu.com
License: UNKNOWN
Project-URL: Source, https://github.com/eamanu/NotImportChecker/
Project-URL: Bug Reports, https://github.com/eamanu/NotImportChecker/issues
Keywords: development import checker
Platform: UNKNOWN
Classifier: Development Status :: 4 - Beta
Classifier: Intended Audience :: Developers
Classifier: Topic :: Software Development :: Build Tools
Classifier: License :: OSI Approved :: GNU General Public License v3 or later (GPLv3+)
Classifier: Programming Language :: Python :: 2
Classifier: Programming Language :: Python :: 3
